teanglann/__init__.py
teanglann/__main__.py
teanglann/py.typed
teanglann/words.py
teanglann-0.1.1.dist-info/METADATA
teanglann-0.1.1.dist-info/WHEEL
teanglann-0.1.1.dist-info/entry_points.txt
teanglann-0.1.1.dist-info/RECORD
