Metadata-Version: 2.3
Name: teanglann
Version: 0.1.1
Summary: Random Irish words from teanglann.ie
Project-URL: Homepage, https://github.com/sopermaf/RandomIrishWord
Author-email: Ferdia Soper Mac Cafraidh <sopermaf@tcd.ie>
Maintainer-email: Ferdia Soper Mac Cafraidh <soeprmaf@tcd.ie>
Classifier: Development Status :: 4 - Beta
Classifier: Programming Language :: Python :: 3 :: Only
Classifier: Programming Language :: Python :: 3.9
Classifier: Programming Language :: Python :: 3.10
Classifier: Programming Language :: Python :: 3.11
Classifier: Programming Language :: Python :: 3.12
Classifier: Programming Language :: Python :: 3.13
Requires-Python: >=3.9
Requires-Dist: bs4
Requires-Dist: click
Requires-Dist: requests
Provides-Extra: dev
Requires-Dist: mypy; extra == 'dev'
Requires-Dist: pre-commit; extra == 'dev'
Requires-Dist: pytest; extra == 'dev'
Requires-Dist: pytest-cov; extra == 'dev'
Requires-Dist: types-beautifulsoup4; extra == 'dev'
Requires-Dist: types-requests; extra == 'dev'
